seafileapi_extended/__init__.py
seafileapi_extended/account.py
seafileapi_extended/admin.py
seafileapi_extended/client.py
seafileapi_extended/exceptions.py
seafileapi_extended/files.py
seafileapi_extended/group.py
seafileapi_extended/groups.py
seafileapi_extended/ping.py
seafileapi_extended/repo.py
seafileapi_extended/repos.py
seafileapi_extended/utils.py
tests/__init__.py
tests/conftest.py
tests/fixtures.py
tests/test_files.py
tests/test_repos.py
tests/utils.py
seafileapi_extended-1.0.8.dist-info/LICENSE
seafileapi_extended-1.0.8.dist-info/METADATA
seafileapi_extended-1.0.8.dist-info/WHEEL
seafileapi_extended-1.0.8.dist-info/top_level.txt
seafileapi_extended-1.0.8.dist-info/RECORD
