Metadata-Version: 2.1
Name: seafileapi-extended
Version: 1.0.8
Summary: Seafile Extended
Home-page: https://github.com/cedvict/seafileapi-extended
Author: Cedvict Loknov
Author-email: Cedvict Loknov <cedvict@gmail.com>
Maintainer-email: Cedvict Loknov <cedvict@gmail.com>
Project-URL: Documentation, https://github.com/haiwen/python-seafile/blob/master/doc.md
Keywords: Seafile,Seafile client,File storage,Cloud storage,File management
Classifier: Development Status :: 3 - Alpha
Classifier: Intended Audience :: Developers
Classifier: Topic :: Internet :: WWW/HTTP :: Session
Classifier: Topic :: Internet :: WWW/HTTP :: WSGI
Classifier: Topic :: Software Development :: Libraries :: Application Frameworks
Classifier: Topic :: Software Development :: Libraries :: Python Modules
Classifier: Framework :: FastAPI
Classifier: License :: OSI Approved :: Apache Software License
Classifier: Programming Language :: Python :: 3.10
Requires-Python: >=3.10
License-File: LICENSE
